odoo/addons/stock_no_negative/README.rst
odoo/addons/stock_no_negative/__init__.py
odoo/addons/stock_no_negative/__manifest__.py
odoo/addons/stock_no_negative/i18n/ar.po
odoo/addons/stock_no_negative/i18n/de.po
odoo/addons/stock_no_negative/i18n/es.po
odoo/addons/stock_no_negative/i18n/fr.po
odoo/addons/stock_no_negative/i18n/hr.po
odoo/addons/stock_no_negative/i18n/it.po
odoo/addons/stock_no_negative/i18n/ja.po
odoo/addons/stock_no_negative/i18n/nl.po
odoo/addons/stock_no_negative/i18n/nl_NL.po
odoo/addons/stock_no_negative/i18n/pt.po
odoo/addons/stock_no_negative/i18n/pt_BR.po
odoo/addons/stock_no_negative/i18n/stock_no_negative.pot
odoo/addons/stock_no_negative/i18n/tr.po
odoo/addons/stock_no_negative/i18n/zh_CN.po
odoo/addons/stock_no_negative/models/__init__.py
odoo/addons/stock_no_negative/models/product.py
odoo/addons/stock_no_negative/models/stock_location.py
odoo/addons/stock_no_negative/models/stock_quant.py
odoo/addons/stock_no_negative/readme/CONFIGURE.md
odoo/addons/stock_no_negative/readme/CONTRIBUTORS.md
odoo/addons/stock_no_negative/readme/DESCRIPTION.md
odoo/addons/stock_no_negative/readme/HISTORY.md
odoo/addons/stock_no_negative/readme/USAGE.md
odoo/addons/stock_no_negative/static/description/icon.png
odoo/addons/stock_no_negative/static/description/index.html
odoo/addons/stock_no_negative/tests/__init__.py
odoo/addons/stock_no_negative/tests/test_stock_no_negative.py
odoo/addons/stock_no_negative/views/product_product_views.xml
odoo/addons/stock_no_negative/views/stock_location_views.xml
odoo_addon_stock_no_negative-18.0.1.0.2.10.dist-info/METADATA
odoo_addon_stock_no_negative-18.0.1.0.2.10.dist-info/WHEEL
odoo_addon_stock_no_negative-18.0.1.0.2.10.dist-info/top_level.txt
odoo_addon_stock_no_negative-18.0.1.0.2.10.dist-info/RECORD
