Metadata-Version: 2.1
Name: odoo-addon-stock_no_negative
Version: 18.0.1.0.2.10
Requires-Python: >=3.10
Requires-Dist: odoo==18.0.*
Summary: Disallow negative stock levels by default
Home-page: https://github.com/OCA/stock-logistics-workflow
License: AGPL-3
Author: Akretion,Odoo Community Association (OCA)
Author-email: support@odoo-community.org
Classifier: Programming Language :: Python
Classifier: Framework :: Odoo
Classifier: Framework :: Odoo :: 18.0
Classifier: License :: OSI Approved :: GNU Affero General Public License v3
